{
    "sourceFile": "src/components/layouts_clients/AppNavbar.vue",
    "activeCommit": 0,
    "commits": [
        {
            "activePatchIndex": 26,
            "patches": [
                {
                    "date": 1747926893203,
                    "content": "Index: \n===================================================================\n--- \n+++ \n"
                },
                {
                    "date": 1747926902878,
                    "content": "Index: \n===================================================================\n--- \n+++ \n@@ -69,9 +69,9 @@\n \r\n             </div>\r\n \r\n           \r\n-            <button class=\"hidden md:block cursor-pointer text-black hover:underline text-sm sm:text-base te\">\r\n+            <button class=\"hidden md:block cursor-pointer text-black hover:underline text-sm sm:text-base \">\r\n                 {{ $t('navbar.login') }}\r\n             </button>\r\n             <button\r\n                 class=\"bg-white text-green-600 px-3 py-1 rounded hover:bg-green-100 cursor-pointer text-sm sm:text-base \">\r\n"
                },
                {
                    "date": 1747973511928,
                    "content": "Index: \n===================================================================\n--- \n+++ \n@@ -69,9 +69,9 @@\n \r\n             </div>\r\n \r\n           \r\n-            <button class=\"hidden md:block cursor-pointer text-black hover:underline text-sm sm:text-base \">\r\n+            <button class=\"hidden md:block cursor-pointer text-black hover:underline text-sm sm:text-base\">\r\n                 {{ $t('navbar.login') }}\r\n             </button>\r\n             <button\r\n                 class=\"bg-white text-green-600 px-3 py-1 rounded hover:bg-green-100 cursor-pointer text-sm sm:text-base \">\r\n@@ -99,10 +99,14 @@\n \r\n <script lang=\"ts\" setup>\r\n import { ref, onMounted, onBeforeUnmount,defineEmits } from 'vue'\r\n \r\n-const windowWidth = ref(window.innerWidth)\r\n+const windowWidth = ref(globalThis.innerWidth)\r\n \r\n+const updateWidth = () => {\r\n+    windowWidth.value = globalThis.innerWidth\r\n+}\r\n+\r\n const emit = defineEmits(['toggle-sidebar'])\r\n const showDropdown = ref(false)\r\n const toggleDropdown = () => {\r\n   showDropdown.value = !showDropdown.value\r\n"
                },
                {
                    "date": 1747973538657,
                    "content": "Index: \n===================================================================\n--- \n+++ \n@@ -99,14 +99,10 @@\n \r\n <script lang=\"ts\" setup>\r\n import { ref, onMounted, onBeforeUnmount,defineEmits } from 'vue'\r\n \r\n-const windowWidth = ref(globalThis.innerWidth)\r\n+const windowWidth = ref(window.innerWidth)\r\n \r\n-const updateWidth = () => {\r\n-    windowWidth.value = globalThis.innerWidth\r\n-}\r\n-\r\n const emit = defineEmits(['toggle-sidebar'])\r\n const showDropdown = ref(false)\r\n const toggleDropdown = () => {\r\n   showDropdown.value = !showDropdown.value\r\n"
                },
                {
                    "date": 1747973576028,
                    "content": "Index: \n===================================================================\n--- \n+++ \n@@ -99,8 +99,9 @@\n \r\n <script lang=\"ts\" setup>\r\n import { ref, onMounted, onBeforeUnmount,defineEmits } from 'vue'\r\n \r\n+declare var window: any;\r\n const windowWidth = ref(window.innerWidth)\r\n \r\n const emit = defineEmits(['toggle-sidebar'])\r\n const showDropdown = ref(false)\r\n"
                },
                {
                    "date": 1747973582231,
                    "content": "Index: \n===================================================================\n--- \n+++ \n@@ -98,9 +98,9 @@\n </template>\r\n \r\n <script lang=\"ts\" setup>\r\n import { ref, onMounted, onBeforeUnmount,defineEmits } from 'vue'\r\n-\r\n+import {}\r\n declare var window: any;\r\n const windowWidth = ref(window.innerWidth)\r\n \r\n const emit = defineEmits(['toggle-sidebar'])\r\n"
                },
                {
                    "date": 1747973626029,
                    "content": "Index: \n===================================================================\n--- \n+++ \n@@ -98,9 +98,11 @@\n </template>\r\n \r\n <script lang=\"ts\" setup>\r\n import { ref, onMounted, onBeforeUnmount,defineEmits } from 'vue'\r\n-import {}\r\n+import { useI18n } from 'vue-i18n';\r\n+\r\n+const { t } = useI18n();\r\n declare var window: any;\r\n const windowWidth = ref(window.innerWidth)\r\n \r\n const emit = defineEmits(['toggle-sidebar'])\r\n"
                },
                {
                    "date": 1747973676930,
                    "content": "Index: \n===================================================================\n--- \n+++ \n@@ -91,9 +91,9 @@\n         <select class=\" text-white px-2 py-1 h-9 focus:outline-none cursor-pointer browse\">\r\n             <option value=\"all\"><i>{{ $t('navbar.browse') }}</i></option>\r\n         </select>\r\n         <button class=\" cursor-pointer text-black hover:underline text-sm sm:text-base\">\r\n-            {{ $t('navbar.mybooks') }}\r\n+            {{ t('navbar.mybooks') }}\r\n         </button>\r\n     </div>\r\n </template>\r\n \r\n"
                },
                {
                    "date": 1747973694164,
                    "content": "Index: \n===================================================================\n--- \n+++ \n@@ -11,13 +11,13 @@\n                 </div>\r\n                 <div class=\"flex gap-5\">\r\n                     <router-link to=\"/client/profile\">\r\n                     <button class=\"hidden md:block cursor-pointer text-black hover:underline mt-2 text-sm sm:text-base\">\r\n-                       {{ $t('navbar.mybooks') }}\r\n+                       {{ t('navbar.mybooks') }}\r\n                     </button>\r\n                     </router-link>\r\n                     <select class=\"hidden md:block text-black px-2 py-1 h-9 focus:outline-none cursor-pointer browse\">\r\n-                        <option value=\"all\"><i>{{ $t('navbar.browse') }}</i></option>\r\n+                        <option value=\"all\"><i>{{ t('navbar.browse') }}</i></option>\r\n                     </select>\r\n \r\n                 </div>\r\n             </div>\r\n@@ -44,13 +44,13 @@\n           <div class=\"flex flex-col space-y-2\">\r\n             <select\r\n               class=\"bg-green-600 text-white px-2 py-1 h-9 focus:outline-none cursor-pointer rounded\"\r\n             >\r\n-              <option value=\"all\">{{ $t('navbar.all') }}</option>\r\n+              <option value=\"all\">{{ t('navbar.all') }}</option>\r\n             </select>\r\n             <input\r\n               type=\"text\"\r\n-              :placeholder=\"$t('navbar.search') + '..........'\"\r\n+              :placeholder=\"t('navbar.search') + '..........'\"\r\n              \r\n               class=\"focus:outline-none text-black shadow-md h-9 py-1 pl-3 rounded\"\r\n             />\r\n           </div>\r\n@@ -60,23 +60,23 @@\n             </div>\r\n             <div class=\" hidden lg:block  flex-col sm:flex-row items-center  w-full sm:w-auto mb-3 sm:mb-0  search-all\">\r\n                 <select\r\n                     class=\"custom-select bg-green-600 all-input shadow-md  text-white px-2 py-1 h-9 focus:outline-none cursor-pointer w-full sm:w-auto\">\r\n-                    <option value=\"all\">{{ $t('navbar.all') }}</option>\r\n+                    <option value=\"all\">{{ t('navbar.all') }}</option>\r\n                 </select>\r\n \r\n-                <input type=\"text\" :placeholder=\"$t('navbar.search') + '..........'\"\r\n+                <input type=\"text\" :placeholder=\"t('navbar.search') + '..........'\"\r\n                     class=\"focus:outline-none text-black shadow-md h-9 py-1 pl-3 w-full sm:w-64\" />\r\n \r\n             </div>\r\n \r\n           \r\n             <button class=\"hidden md:block cursor-pointer text-black hover:underline text-sm sm:text-base\">\r\n-                {{ $t('navbar.login') }}\r\n+                {{ t('navbar.login') }}\r\n             </button>\r\n             <button\r\n                 class=\"bg-white text-green-600 px-3 py-1 rounded hover:bg-green-100 cursor-pointer text-sm sm:text-base \">\r\n-                {{ $t('navbar.signup') }}\r\n+                {{ t('navbar.signup') }}\r\n             </button>\r\n \r\n             <button class=\"cursor-pointer\" @click=\"emit('toggle-sidebar')\">\r\n                 <span\r\n@@ -88,9 +88,9 @@\n         </div>\r\n     </header>\r\n     <div class=\" md:hidden flex justify-center gap-5 items-center py-3 container bg-gray-400 mx-auto\">\r\n         <select class=\" text-white px-2 py-1 h-9 focus:outline-none cursor-pointer browse\">\r\n-            <option value=\"all\"><i>{{ $t('navbar.browse') }}</i></option>\r\n+            <option value=\"all\"><i>{{ t('navbar.browse') }}</i></option>\r\n         </select>\r\n         <button class=\" cursor-pointer text-black hover:underline text-sm sm:text-base\">\r\n             {{ t('navbar.mybooks') }}\r\n         </button>\r\n"
                },
                {
                    "date": 1748065495045,
                    "content": "Index: \n===================================================================\n--- \n+++ \n@@ -42,9 +42,9 @@\n           class=\"absolute right-0 mt-2 bg-white shadow-lg rounded-md  w-[250px] p-3 z-50\"\r\n         >\r\n           <div class=\"flex flex-col space-y-2\">\r\n             <select\r\n-              class=\"bg-green-600 text-white px-2 py-1 h-9 focus:outline-none cursor-pointer rounded\"\r\n+              class=\"bg-green-600 shadow-md text-white px-2 py-1 h-9 focus:outline-none cursor-pointer rounded-l sm:rounded-l\"\r\n             >\r\n               <option value=\"all\">{{ t('navbar.all') }}</option>\r\n             </select>\r\n             <input\r\n"
                },
                {
                    "date": 1748065591008,
                    "content": "Index: \n===================================================================\n--- \n+++ \n@@ -42,9 +42,9 @@\n           class=\"absolute right-0 mt-2 bg-white shadow-lg rounded-md  w-[250px] p-3 z-50\"\r\n         >\r\n           <div class=\"flex flex-col space-y-2\">\r\n             <select\r\n-              class=\"bg-green-600 shadow-md text-white px-2 py-1 h-9 focus:outline-none cursor-pointer rounded-l sm:rounded-l\"\r\n+              class=\"bg-green-600 shadow-md text-white px-2 py-1 h-9 focus:outline-none cursor-pointer rounded- sm:rounded-l\"\r\n             >\r\n               <option value=\"all\">{{ t('navbar.all') }}</option>\r\n             </select>\r\n             <input\r\n"
                },
                {
                    "date": 1748065599318,
                    "content": "Index: \n===================================================================\n--- \n+++ \n@@ -42,9 +42,9 @@\n           class=\"absolute right-0 mt-2 bg-white shadow-lg rounded-md  w-[250px] p-3 z-50\"\r\n         >\r\n           <div class=\"flex flex-col space-y-2\">\r\n             <select\r\n-              class=\"bg-green-600 shadow-md text-white px-2 py-1 h-9 focus:outline-none cursor-pointer rounded- sm:rounded-l\"\r\n+              class=\"bg-green-600 shadow-md text-white px-2 py-1 h-9 focus:outline-none cursor-pointer rounded-xl sm:rounded-l\"\r\n             >\r\n               <option value=\"all\">{{ t('navbar.all') }}</option>\r\n             </select>\r\n             <input\r\n"
                },
                {
                    "date": 1748065824962,
                    "content": "Index: \n===================================================================\n--- \n+++ \n@@ -59,9 +59,9 @@\n                 </div>\r\n             </div>\r\n             <div class=\" hidden lg:block  flex-col sm:flex-row items-center  w-full sm:w-auto mb-3 sm:mb-0  search-all\">\r\n                 <select\r\n-                    class=\"custom-select bg-green-600 all-input shadow-md  text-white px-2 py-1 h-9 focus:outline-none cursor-pointer w-full sm:w-auto\">\r\n+                    class=\"bg-green-600 shadow-md text-white px-2 py-1 h-9 focus:outline-none cursor-pointer rounded-l sm:rounded-l\">\r\n                     <option value=\"all\">{{ t('navbar.all') }}</option>\r\n                 </select>\r\n \r\n                 <input type=\"text\" :placeholder=\"t('navbar.search') + '..........'\"\r\n"
                },
                {
                    "date": 1748087517505,
                    "content": "Index: \n===================================================================\n--- \n+++ \n@@ -61,8 +61,10 @@\n             <div class=\" hidden lg:block  flex-col sm:flex-row items-center  w-full sm:w-auto mb-3 sm:mb-0  search-all\">\r\n                 <select\r\n                     class=\"bg-green-600 shadow-md text-white px-2 py-1 h-9 focus:outline-none cursor-pointer rounded-l sm:rounded-l\">\r\n                     <option value=\"all\">{{ t('navbar.all') }}</option>\r\n+                    <option value=\"all\">{{ t('navbar.all') }}</option>\r\n+                    <option value=\"all\">{{ t('navbar.all') }}</option>\r\n                 </select>\r\n \r\n                 <input type=\"text\" :placeholder=\"t('navbar.search') + '..........'\"\r\n                     class=\"focus:outline-none text-black shadow-md h-9 py-1 pl-3 w-full sm:w-64\" />\r\n"
                },
                {
                    "date": 1748087526474,
                    "content": "Index: \n===================================================================\n--- \n+++ \n@@ -63,8 +63,10 @@\n                     class=\"bg-green-600 shadow-md text-white px-2 py-1 h-9 focus:outline-none cursor-pointer rounded-l sm:rounded-l\">\r\n                     <option value=\"all\">{{ t('navbar.all') }}</option>\r\n                     <option value=\"all\">{{ t('navbar.all') }}</option>\r\n                     <option value=\"all\">{{ t('navbar.all') }}</option>\r\n+                    <option value=\"all\">{{ t('navbar.all') }}</option>\r\n+                    <option value=\"all\">{{ t('navbar.all') }}</option>\r\n                 </select>\r\n \r\n                 <input type=\"text\" :placeholder=\"t('navbar.search') + '..........'\"\r\n                     class=\"focus:outline-none text-black shadow-md h-9 py-1 pl-3 w-full sm:w-64\" />\r\n"
                },
                {
                    "date": 1748087552412,
                    "content": "Index: \n===================================================================\n--- \n+++ \n@@ -61,12 +61,12 @@\n             <div class=\" hidden lg:block  flex-col sm:flex-row items-center  w-full sm:w-auto mb-3 sm:mb-0  search-all\">\r\n                 <select\r\n                     class=\"bg-green-600 shadow-md text-white px-2 py-1 h-9 focus:outline-none cursor-pointer rounded-l sm:rounded-l\">\r\n                     <option value=\"all\">{{ t('navbar.all') }}</option>\r\n+                    <option value=\"all\"></option>\r\n                     <option value=\"all\">{{ t('navbar.all') }}</option>\r\n                     <option value=\"all\">{{ t('navbar.all') }}</option>\r\n                     <option value=\"all\">{{ t('navbar.all') }}</option>\r\n-                    <option value=\"all\">{{ t('navbar.all') }}</option>\r\n                 </select>\r\n \r\n                 <input type=\"text\" :placeholder=\"t('navbar.search') + '..........'\"\r\n                     class=\"focus:outline-none text-black shadow-md h-9 py-1 pl-3 w-full sm:w-64\" />\r\n"
                },
                {
                    "date": 1748087557889,
                    "content": "Index: \n===================================================================\n--- \n+++ \n@@ -61,9 +61,9 @@\n             <div class=\" hidden lg:block  flex-col sm:flex-row items-center  w-full sm:w-auto mb-3 sm:mb-0  search-all\">\r\n                 <select\r\n                     class=\"bg-green-600 shadow-md text-white px-2 py-1 h-9 focus:outline-none cursor-pointer rounded-l sm:rounded-l\">\r\n                     <option value=\"all\">{{ t('navbar.all') }}</option>\r\n-                    <option value=\"all\"></option>\r\n+                    <option value=\"all\"><title></title></option>\r\n                     <option value=\"all\">{{ t('navbar.all') }}</option>\r\n                     <option value=\"all\">{{ t('navbar.all') }}</option>\r\n                     <option value=\"all\">{{ t('navbar.all') }}</option>\r\n                 </select>\r\n"
                },
                {
                    "date": 1748087572921,
                    "content": "Index: \n===================================================================\n--- \n+++ \n@@ -61,12 +61,12 @@\n             <div class=\" hidden lg:block  flex-col sm:flex-row items-center  w-full sm:w-auto mb-3 sm:mb-0  search-all\">\r\n                 <select\r\n                     class=\"bg-green-600 shadow-md text-white px-2 py-1 h-9 focus:outline-none cursor-pointer rounded-l sm:rounded-l\">\r\n                     <option value=\"all\">{{ t('navbar.all') }}</option>\r\n-                    <option value=\"all\"><title></title></option>\r\n+                    <option value=\"all\">title</option>\r\n+                    <option value=\"all\">au</option>\r\n                     <option value=\"all\">{{ t('navbar.all') }}</option>\r\n                     <option value=\"all\">{{ t('navbar.all') }}</option>\r\n-                    <option value=\"all\">{{ t('navbar.all') }}</option>\r\n                 </select>\r\n \r\n                 <input type=\"text\" :placeholder=\"t('navbar.search') + '..........'\"\r\n                     class=\"focus:outline-none text-black shadow-md h-9 py-1 pl-3 w-full sm:w-64\" />\r\n"
                },
                {
                    "date": 1748087578285,
                    "content": "Index: \n===================================================================\n--- \n+++ \n@@ -62,9 +62,9 @@\n                 <select\r\n                     class=\"bg-green-600 shadow-md text-white px-2 py-1 h-9 focus:outline-none cursor-pointer rounded-l sm:rounded-l\">\r\n                     <option value=\"all\">{{ t('navbar.all') }}</option>\r\n                     <option value=\"all\">title</option>\r\n-                    <option value=\"all\">au</option>\r\n+                    <option value=\"all\">autho</option>\r\n                     <option value=\"all\">{{ t('navbar.all') }}</option>\r\n                     <option value=\"all\">{{ t('navbar.all') }}</option>\r\n                 </select>\r\n \r\n"
                },
                {
                    "date": 1748087641048,
                    "content": "Index: \n===================================================================\n--- \n+++ \n@@ -62,11 +62,10 @@\n                 <select\r\n                     class=\"bg-green-600 shadow-md text-white px-2 py-1 h-9 focus:outline-none cursor-pointer rounded-l sm:rounded-l\">\r\n                     <option value=\"all\">{{ t('navbar.all') }}</option>\r\n                     <option value=\"all\">title</option>\r\n-                    <option value=\"all\">autho</option>\r\n-                    <option value=\"all\">{{ t('navbar.all') }}</option>\r\n-                    <option value=\"all\">{{ t('navbar.all') }}</option>\r\n+                    <option value=\"all\">author</option>\r\n+                    \r\n                 </select>\r\n \r\n                 <input type=\"text\" :placeholder=\"t('navbar.search') + '..........'\"\r\n                     class=\"focus:outline-none text-black shadow-md h-9 py-1 pl-3 w-full sm:w-64\" />\r\n"
                },
                {
                    "date": 1748090772670,
                    "content": "Index: \n===================================================================\n--- \n+++ \n@@ -61,9 +61,9 @@\n             <div class=\" hidden lg:block  flex-col sm:flex-row items-center  w-full sm:w-auto mb-3 sm:mb-0  search-all\">\r\n                 <select\r\n                     class=\"bg-green-600 shadow-md text-white px-2 py-1 h-9 focus:outline-none cursor-pointer rounded-l sm:rounded-l\">\r\n                     <option value=\"all\">{{ t('navbar.all') }}</option>\r\n-                    <option value=\"all\">title</option>\r\n+                    <option  value=\"all\">title</option>\r\n                     <option value=\"all\">author</option>\r\n                     \r\n                 </select>\r\n \r\n"
                },
                {
                    "date": 1748090779705,
                    "content": "Index: \n===================================================================\n--- \n+++ \n@@ -61,9 +61,9 @@\n             <div class=\" hidden lg:block  flex-col sm:flex-row items-center  w-full sm:w-auto mb-3 sm:mb-0  search-all\">\r\n                 <select\r\n                     class=\"bg-green-600 shadow-md text-white px-2 py-1 h-9 focus:outline-none cursor-pointer rounded-l sm:rounded-l\">\r\n                     <option value=\"all\">{{ t('navbar.all') }}</option>\r\n-                    <option  value=\"all\">title</option>\r\n+                    <option class=\"\" value=\"all\">title</option>\r\n                     <option value=\"all\">author</option>\r\n                     \r\n                 </select>\r\n \r\n"
                },
                {
                    "date": 1748090786667,
                    "content": "Index: \n===================================================================\n--- \n+++ \n@@ -61,9 +61,9 @@\n             <div class=\" hidden lg:block  flex-col sm:flex-row items-center  w-full sm:w-auto mb-3 sm:mb-0  search-all\">\r\n                 <select\r\n                     class=\"bg-green-600 shadow-md text-white px-2 py-1 h-9 focus:outline-none cursor-pointer rounded-l sm:rounded-l\">\r\n                     <option value=\"all\">{{ t('navbar.all') }}</option>\r\n-                    <option class=\"\" value=\"all\">title</option>\r\n+                    <option class=\"bg-white\" value=\"all\">title</option>\r\n                     <option value=\"all\">author</option>\r\n                     \r\n                 </select>\r\n \r\n"
                },
                {
                    "date": 1748090809517,
                    "content": "Index: \n===================================================================\n--- \n+++ \n@@ -60,11 +60,11 @@\n             </div>\r\n             <div class=\" hidden lg:block  flex-col sm:flex-row items-center  w-full sm:w-auto mb-3 sm:mb-0  search-all\">\r\n                 <select\r\n                     class=\"bg-green-600 shadow-md text-white px-2 py-1 h-9 focus:outline-none cursor-pointer rounded-l sm:rounded-l\">\r\n-                    <option value=\"all\">{{ t('navbar.all') }}</option>\r\n+                    <option class=\"bg-white\" value=\"all\">{{ t('navbar.all') }}</option>\r\n                     <option class=\"bg-white\" value=\"all\">title</option>\r\n-                    <option value=\"all\">author</option>\r\n+                    <option  value=\"all\">author</option>\r\n                     \r\n                 </select>\r\n \r\n                 <input type=\"text\" :placeholder=\"t('navbar.search') + '..........'\"\r\n"
                },
                {
                    "date": 1748090815499,
                    "content": "Index: \n===================================================================\n--- \n+++ \n@@ -60,11 +60,11 @@\n             </div>\r\n             <div class=\" hidden lg:block  flex-col sm:flex-row items-center  w-full sm:w-auto mb-3 sm:mb-0  search-all\">\r\n                 <select\r\n                     class=\"bg-green-600 shadow-md text-white px-2 py-1 h-9 focus:outline-none cursor-pointer rounded-l sm:rounded-l\">\r\n-                    <option class=\"bg-white\" value=\"all\">{{ t('navbar.all') }}</option>\r\n+                    <option class=\"bg-white \" value=\"all\">{{ t('navbar.all') }}</option>\r\n                     <option class=\"bg-white\" value=\"all\">title</option>\r\n-                    <option  value=\"all\">author</option>\r\n+                    <option class=\"bg-white\" value=\"all\">author</option>\r\n                     \r\n                 </select>\r\n \r\n                 <input type=\"text\" :placeholder=\"t('navbar.search') + '..........'\"\r\n"
                },
                {
                    "date": 1748090824191,
                    "content": "Index: \n===================================================================\n--- \n+++ \n@@ -60,10 +60,10 @@\n             </div>\r\n             <div class=\" hidden lg:block  flex-col sm:flex-row items-center  w-full sm:w-auto mb-3 sm:mb-0  search-all\">\r\n                 <select\r\n                     class=\"bg-green-600 shadow-md text-white px-2 py-1 h-9 focus:outline-none cursor-pointer rounded-l sm:rounded-l\">\r\n-                    <option class=\"bg-white \" value=\"all\">{{ t('navbar.all') }}</option>\r\n-                    <option class=\"bg-white\" value=\"all\">title</option>\r\n+                    <option class=\"bg-white text-black\" value=\"all\">{{ t('navbar.all') }}</option>\r\n+                    <option class=\"bg-white  text-black\" value=\"all\">title</option>\r\n                     <option class=\"bg-white\" value=\"all\">author</option>\r\n                     \r\n                 </select>\r\n \r\n"
                },
                {
                    "date": 1748091004197,
                    "content": "Index: \n===================================================================\n--- \n+++ \n@@ -14,11 +14,11 @@\n                     <button class=\"hidden md:block cursor-pointer text-black hover:underline mt-2 text-sm sm:text-base\">\r\n                        {{ t('navbar.mybooks') }}\r\n                     </button>\r\n                     </router-link>\r\n-                    <select class=\"hidden md:block text-black px-2 py-1 h-9 focus:outline-none cursor-pointer browse\">\r\n+                    <!-- <select class=\"hidden md:block text-black px-2 py-1 h-9 focus:outline-none cursor-pointer browse\">\r\n                         <option value=\"all\"><i>{{ t('navbar.browse') }}</i></option>\r\n-                    </select>\r\n+                    </select> -->\r\n \r\n                 </div>\r\n             </div>\r\n         </div>\r\n@@ -62,9 +62,9 @@\n                 <select\r\n                     class=\"bg-green-600 shadow-md text-white px-2 py-1 h-9 focus:outline-none cursor-pointer rounded-l sm:rounded-l\">\r\n                     <option class=\"bg-white text-black\" value=\"all\">{{ t('navbar.all') }}</option>\r\n                     <option class=\"bg-white  text-black\" value=\"all\">title</option>\r\n-                    <option class=\"bg-white\" value=\"all\">author</option>\r\n+                    <option class=\"bg-white  text-black\" value=\"all\">author</option>\r\n                     \r\n                 </select>\r\n \r\n                 <input type=\"text\" :placeholder=\"t('navbar.search') + '..........'\"\r\n"
                }
            ],
            "date": 1747926893203,
            "name": "Commit-0",
            "content": "can you improve my responseive \"\"<template>\r\n\r\n    <header class=\"text-white flex justify-between  items-center  py-3 container mx-auto \">\r\n        <!-- Left: Logo and Title and input -->\r\n        <div class=\"logo-search\">\r\n            <div class=\"flex items-center gap-2 w-full sm:w-auto mb-3  sm:mb-0 logo-library\">\r\n                <div>\r\n                    <router-link to=\"/client/home\">\r\n                    <img src=\"../../assets/images/Librarylogo.png\" alt=\"Quest College\" class=\"w-40 sm:w-50 mt-3 \" />\r\n                </router-link>\r\n                </div>\r\n                <div class=\"flex gap-5\">\r\n                    <router-link to=\"/client/profile\">\r\n                    <button class=\"hidden md:block cursor-pointer text-black hover:underline mt-2 text-sm sm:text-base\">\r\n                       {{ $t('navbar.mybooks') }}\r\n                    </button>\r\n                    </router-link>\r\n                    <select class=\"hidden md:block text-black px-2 py-1 h-9 focus:outline-none cursor-pointer browse\">\r\n                        <option value=\"all\"><i>{{ $t('navbar.browse') }}</i></option>\r\n                    </select>\r\n\r\n                </div>\r\n            </div>\r\n        </div>\r\n\r\n\r\n \r\n        <!-- 1 Right: menu Auth Buttons -->\r\n        <div class=\" navbar-menus flex items-center gap-3 w-full  sm:w-auto justify-end sm:justify-start\"\r\n            style=\"padding-right:-20px;\">\r\n            <!-- Center: Dropdown + Search -->\r\n            <div class=\"block lg:hidden\">\r\n                <div class=\"ml-24 mt-2\">\r\n                         <div class=\"relative\">\r\n        <div class=\"flex items-center gap-1 text-white cursor-pointer\" @click=\"toggleDropdown\">\r\n         <i class=\"fas fa-search text-xl w-5 text-black mb-2 \"></i>\r\n        </div>\r\n\r\n        <!-- Dropdown Search Form -->\r\n        <div\r\n          v-if=\"showDropdown\"\r\n          class=\"absolute right-0 mt-2 bg-white shadow-lg rounded-md  w-[250px] p-3 z-50\"\r\n        >\r\n          <div class=\"flex flex-col space-y-2\">\r\n            <select\r\n              class=\"bg-green-600 text-white px-2 py-1 h-9 focus:outline-none cursor-pointer rounded\"\r\n            >\r\n              <option value=\"all\">{{ $t('navbar.all') }}</option>\r\n            </select>\r\n            <input\r\n              type=\"text\"\r\n              :placeholder=\"$t('navbar.search') + '..........'\"\r\n             \r\n              class=\"focus:outline-none text-black shadow-md h-9 py-1 pl-3 rounded\"\r\n            />\r\n          </div>\r\n        </div>\r\n      </div>\r\n                </div>\r\n            </div>\r\n            <div class=\" hidden lg:block  flex-col sm:flex-row items-center  w-full sm:w-auto mb-3 sm:mb-0  search-all\">\r\n                <select\r\n                    class=\"custom-select bg-green-600 all-input shadow-md  text-white px-2 py-1 h-9 focus:outline-none cursor-pointer w-full sm:w-auto\">\r\n                    <option value=\"all\">{{ $t('navbar.all') }}</option>\r\n                </select>\r\n\r\n                <input type=\"text\" :placeholder=\"$t('navbar.search') + '..........'\"\r\n                    class=\"focus:outline-none text-black shadow-md h-9 py-1 pl-3 w-full sm:w-64\" />\r\n\r\n            </div>\r\n\r\n          \r\n            <button class=\"hidden md:block cursor-pointer text-black hover:underline text-sm sm:text-base te\">\r\n                {{ $t('navbar.login') }}\r\n            </button>\r\n            <button\r\n                class=\"bg-white text-green-600 px-3 py-1 rounded hover:bg-green-100 cursor-pointer text-sm sm:text-base \">\r\n                {{ $t('navbar.signup') }}\r\n            </button>\r\n\r\n            <button class=\"cursor-pointer\" @click=\"emit('toggle-sidebar')\">\r\n                <span\r\n                    class=\"inline-flex items-center justify-center w-10 h-10 rounded-full transition-colors duration-300 hover:bg-green-600\">\r\n                    <i class=\"fa-solid fa-bars text-green-600 hover:text-white\"></i>\r\n                </span>\r\n            </button>\r\n\r\n        </div>\r\n    </header>\r\n    <div class=\" md:hidden flex justify-center gap-5 items-center py-3 container bg-gray-400 mx-auto\">\r\n        <select class=\" text-white px-2 py-1 h-9 focus:outline-none cursor-pointer browse\">\r\n            <option value=\"all\"><i>{{ $t('navbar.browse') }}</i></option>\r\n        </select>\r\n        <button class=\" cursor-pointer text-black hover:underline text-sm sm:text-base\">\r\n            {{ $t('navbar.mybooks') }}\r\n        </button>\r\n    </div>\r\n</template>\r\n\r\n<script lang=\"ts\" setup>\r\nimport { ref, onMounted, onBeforeUnmount,defineEmits } from 'vue'\r\n\r\nconst windowWidth = ref(window.innerWidth)\r\n\r\nconst emit = defineEmits(['toggle-sidebar'])\r\nconst showDropdown = ref(false)\r\nconst toggleDropdown = () => {\r\n  showDropdown.value = !showDropdown.value\r\n}\r\nconst updateWidth = () => {\r\n    windowWidth.value = window.innerWidth\r\n}\r\n\r\nonMounted(() => {\r\n    window.addEventListener('resize', updateWidth)\r\n})\r\n\r\nonBeforeUnmount(() => {\r\n    window.removeEventListener('resize', updateWidth)\r\n})\r\n\r\n</script>\r\n\r\n<style scoped></style>\r\n"
        }
    ]
}